[
  {
    "constant": false,
    "inputs": [
      {
        "name": "nonce",
        "type": "bytes32"
      }
    ],
    "name": "claimRipeMD160Reward",
    "outputs": [
      {
        "name": "success",
        "type": "bool"
      }
    ],
    "payable": false,
    "type": "function"
  },
  {
    "constant": true,
    "inputs": [
      
    ],
    "name": "name",
    "outputs": [
      {
        "name": "",
        "type": "string",
        "value": "FloatCoin"
      }
    ],
    "payable": false,
    "type": "function"
  },
  {
    "constant": true,
    "inputs": [
      
    ],
    "name": "currentDoubleSHA256Challenge",
    "outputs": [
      {
        "name": "",
        "type": "bytes32",
        "value": "0x4ad9c2b02507d3c668f941c716e7d2d95f8e0288d788db07895920c97f00aa96"
      }
    ],
    "payable": false,
    "type": "function"
  },
  {
    "constant": false,
    "inputs": [
      {
        "name": "_spender",
        "type": "address"
      },
      {
        "name": "_value",
        "type": "uint256"
      }
    ],
    "name": "approve",
    "outputs": [
      {
        "name": "success",
        "type": "bool"
      }
    ],
    "payable": false,
    "type": "function"
  },
  {
    "constant": true,
    "inputs": [
      
    ],
    "name": "timeOfLastDoubleSHA256Proof",
    "outputs": [
      {
        "name": "",
        "type": "uint256",
        "value": "1506177878"
      }
    ],
    "payable": false,
    "type": "function"
  },
  {
    "constant": false,
    "inputs": [
      
    ],
    "name": "claimBlockReward",
    "outputs": [
      {
        "name": "success",
        "type": "bool"
      }
    ],
    "payable": false,
    "type": "function"
  },
  {
    "constant": true,
    "inputs": [
      
    ],
    "name": "totalSupply",
    "outputs": [
      {
        "name": "",
        "type": "uint256",
        "value": "0"
      }
    ],
    "payable": false,
    "type": "function"
  },
  {
    "constant": true,
    "inputs": [
      
    ],
    "name": "currentRipeMD160Challenge",
    "outputs": [
      {
        "name": "",
        "type": "bytes32",
        "value": "0x4ad9c2b02507d3c668f941c716e7d2d95f8e0288d788db07895920c97f00aa96"
      }
    ],
    "payable": false,
    "type": "function"
  },
  {
    "constant": false,
    "inputs": [
      {
        "name": "_from",
        "type": "address"
      },
      {
        "name": "_to",
        "type": "address"
      },
      {
        "name": "_value",
        "type": "uint256"
      }
    ],
    "name": "transferFrom",
    "outputs": [
      {
        "name": "success",
        "type": "bool"
      }
    ],
    "payable": false,
    "type": "function"
  },
  {
    "constant": true,
    "inputs": [
      
    ],
    "name": "currentKeccak256Challenge",
    "outputs": [
      {
        "name": "",
        "type": "bytes32",
        "value": "0x4ad9c2b02507d3c668f941c716e7d2d95f8e0288d788db07895920c97f00aa96"
      }
    ],
    "payable": false,
    "type": "function"
  },
  {
    "constant": false,
    "inputs": [
      {
        "name": "nonce",
        "type": "bytes32"
      }
    ],
    "name": "claimDoubleSHA256Reward",
    "outputs": [
      {
        "name": "success",
        "type": "bool"
      }
    ],
    "payable": false,
    "type": "function"
  },
  {
    "constant": true,
    "inputs": [
      
    ],
    "name": "decimals",
    "outputs": [
      {
        "name": "",
        "type": "uint8",
        "value": "16"
      }
    ],
    "payable": false,
    "type": "function"
  },
  {
    "constant": true,
    "inputs": [
      
    ],
    "name": "MinedReward",
    "outputs": [
      {
        "name": "",
        "type": "uint256",
        "value": "10000000000000000"
      }
    ],
    "payable": false,
    "type": "function"
  },
  {
    "constant": false,
    "inputs": [
      {
        "name": "_value",
        "type": "uint256"
      }
    ],
    "name": "burn",
    "outputs": [
      {
        "name": "success",
        "type": "bool"
      }
    ],
    "payable": false,
    "type": "function"
  },
  {
    "constant": true,
    "inputs": [
      
    ],
    "name": "timeOfLastKeccak256Proof",
    "outputs": [
      {
        "name": "",
        "type": "uint256",
        "value": "1506177878"
      }
    ],
    "payable": false,
    "type": "function"
  },
  {
    "constant": true,
    "inputs": [
      
    ],
    "name": "Keccak256Difficulty",
    "outputs": [
      {
        "name": "",
        "type": "uint256",
        "value": "1000000"
      }
    ],
    "payable": false,
    "type": "function"
  },
  {
    "constant": true,
    "inputs": [
      
    ],
    "name": "timeOfLastRipeMD160Proof",
    "outputs": [
      {
        "name": "",
        "type": "uint256",
        "value": "0"
      }
    ],
    "payable": false,
    "type": "function"
  },
  {
    "constant": true,
    "inputs": [
      {
        "name": "",
        "type": "address"
      }
    ],
    "name": "balanceOf",
    "outputs": [
      {
        "name": "",
        "type": "uint256",
        "value": "0"
      }
    ],
    "payable": false,
    "type": "function"
  },
  {
    "constant": false,
    "inputs": [
      {
        "name": "_from",
        "type": "address"
      },
      {
        "name": "_value",
        "type": "uint256"
      }
    ],
    "name": "burnFrom",
    "outputs": [
      {
        "name": "success",
        "type": "bool"
      }
    ],
    "payable": false,
    "type": "function"
  },
  {
    "constant": true,
    "inputs": [
      
    ],
    "name": "lastBlock",
    "outputs": [
      {
        "name": "",
        "type": "uint256",
        "value": "944401"
      }
    ],
    "payable": false,
    "type": "function"
  },
  {
    "constant": true,
    "inputs": [
      
    ],
    "name": "timeOfLastProof",
    "outputs": [
      {
        "name": "",
        "type": "uint256",
        "value": "1506177878"
      }
    ],
    "payable": false,
    "type": "function"
  },
  {
    "constant": true,
    "inputs": [
      
    ],
    "name": "symbol",
    "outputs": [
      {
        "name": "",
        "type": "string",
        "value": "FC"
      }
    ],
    "payable": false,
    "type": "function"
  },
  {
    "constant": true,
    "inputs": [
      
    ],
    "name": "DoubleSHA256Difficulty",
    "outputs": [
      {
        "name": "",
        "type": "uint256",
        "value": "1000000"
      }
    ],
    "payable": false,
    "type": "function"
  },
  {
    "constant": false,
    "inputs": [
      {
        "name": "_to",
        "type": "address"
      },
      {
        "name": "_value",
        "type": "uint256"
      }
    ],
    "name": "transfer",
    "outputs": [
      {
        "name": "success",
        "type": "bool"
      }
    ],
    "payable": false,
    "type": "function"
  },
  {
    "constant": true,
    "inputs": [
      
    ],
    "name": "RipeMD160Difficulty",
    "outputs": [
      {
        "name": "",
        "type": "uint256",
        "value": "1000000"
      }
    ],
    "payable": false,
    "type": "function"
  },
  {
    "constant": false,
    "inputs": [
      {
        "name": "_spender",
        "type": "address"
      },
      {
        "name": "_value",
        "type": "uint256"
      },
      {
        "name": "_extraData",
        "type": "bytes"
      }
    ],
    "name": "approveAndCall",
    "outputs": [
      {
        "name": "success",
        "type": "bool"
      }
    ],
    "payable": false,
    "type": "function"
  },
  {
    "constant": true,
    "inputs": [
      {
        "name": "",
        "type": "address"
      },
      {
        "name": "",
        "type": "address"
      }
    ],
    "name": "allowance",
    "outputs": [
      {
        "name": "",
        "type": "uint256",
        "value": "0"
      }
    ],
    "payable": false,
    "type": "function"
  },
  {
    "constant": false,
    "inputs": [
      {
        "name": "nonce",
        "type": "bytes32"
      }
    ],
    "name": "claimKeccak256Reward",
    "outputs": [
      {
        "name": "success",
        "type": "bool"
      }
    ],
    "payable": false,
    "type": "function"
  },
  {
    "constant": true,
    "inputs": [
      
    ],
    "name": "MergedReward",
    "outputs": [
      {
        "name": "",
        "type": "uint256",
        "value": "100000000000000"
      }
    ],
    "payable": false,
    "type": "function"
  },
  {
    "inputs": [
      
    ],
    "payable": false,
    "type": "constructor"
  },
  {
    "anonymous": false,
    "inputs": [
      {
        "indexed": true,
        "name": "from",
        "type": "address"
      },
      {
        "indexed": true,
        "name": "to",
        "type": "address"
      },
      {
        "indexed": false,
        "name": "value",
        "type": "uint256"
      }
    ],
    "name": "Transfer",
    "type": "event"
  },
  {
    "anonymous": false,
    "inputs": [
      {
        "indexed": true,
        "name": "from",
        "type": "address"
      },
      {
        "indexed": false,
        "name": "value",
        "type": "uint256"
      }
    ],
    "name": "Burn",
    "type": "event"
  },
  {
    "anonymous": false,
    "inputs": [
      {
        "indexed": true,
        "name": "claimant",
        "type": "address"
      },
      {
        "indexed": false,
        "name": "value",
        "type": "uint256"
      }
    ],
    "name": "BlockRewardClaimed",
    "type": "event"
  },
  {
    "anonymous": false,
    "inputs": [
      {
        "indexed": true,
        "name": "claimant",
        "type": "address"
      },
      {
        "indexed": false,
        "name": "value",
        "type": "uint256"
      }
    ],
    "name": "DoubleSHA256RewardClaimed",
    "type": "event"
  },
  {
    "anonymous": false,
    "inputs": [
      {
        "indexed": true,
        "name": "claimant",
        "type": "address"
      },
      {
        "indexed": false,
        "name": "value",
        "type": "uint256"
      }
    ],
    "name": "Keccak256RewardClaimed",
    "type": "event"
  },
  {
    "anonymous": false,
    "inputs": [
      {
        "indexed": true,
        "name": "claimant",
        "type": "address"
      },
      {
        "indexed": false,
        "name": "value",
        "type": "uint256"
      }
    ],
    "name": "RipeMD160RewardClaimed",
    "type": "event"
  }
]